pydantic-gsheets/auth/user_oauth.py
pydantic_gsheets/__init__.py
pydantic_gsheets/exceptions.py
pydantic_gsheets/worksheet.py
pydantic_gsheets/auth/__init__.py
pydantic_gsheets/auth/base.py
pydantic_gsheets/auth/factory.py
pydantic_gsheets/auth/user_oauth.py
pydantic_gsheets/types/__init__.py
pydantic_gsheets/types/smartChips_.py
pydantic_gsheets-0.0.8.dist-info/licenses/LICENSE
pydantic_gsheets-0.0.8.dist-info/METADATA
pydantic_gsheets-0.0.8.dist-info/WHEEL
pydantic_gsheets-0.0.8.dist-info/top_level.txt
pydantic_gsheets-0.0.8.dist-info/RECORD
