Metadata-Version: 2.4
Name: pydantic-gsheets
Version: 0.0.8
Summary: A Pydantic integration for Google Sheets
Author-email: Youssef Ben hammouda <youssef@benhammouda.ma>
Project-URL: Homepage, https://github.com/Youssefbenhammouda/pydantic-gsheets
Project-URL: Repository, https://github.com/Youssefbenhammouda/pydantic-gsheets
Project-URL: Issues, https://github.com/Youssefbenhammouda/pydantic-gsheets/issues
Project-URL: Documentation, https://github.com/Youssefbenhammouda/pydantic-gsheets#readme
Requires-Python: >=3.12
License-File: LICENSE
Requires-Dist: google-api-python-client~=2.178.0
Requires-Dist: google-auth-oauthlib~=1.2.2
Requires-Dist: pydantic~=2.11.7
Provides-Extra: test
Requires-Dist: pytest; extra == "test"
Requires-Dist: Faker; extra == "test"
Provides-Extra: docs
Requires-Dist: mkdocs-material>=9.6; extra == "docs"
Provides-Extra: dev
Requires-Dist: pytest; extra == "dev"
Requires-Dist: mkdocs-material>=9.6; extra == "dev"
Dynamic: license-file
